Workbook
Name aporte: 'Simulador Financeiro'!$D$19:$D$19
Name patrimonio: 'Simulador Financeiro'!$D$22:$D$22
Name qtd_anos: 'Simulador Financeiro'!$D$20:$D$20
Name rendimento_carteira: 'Simulador Financeiro'!$D$15:$D$15
Name salario: 'Simulador Financeiro'!$D$14:$D$14
Name sugestao_investimento: 'Simulador Financeiro'!$D$16:$D$16
Name taxa_mensal: 'Simulador Financeiro'!$D$21:$D$21

Sheet Simulador Financeiro
B13: CONFIGURAÇÕES
B14: Salário | D14: 2000
B15: Rendimento Carteira | D15: 0.006
B16: Sugestão de Investimento | D16: =D14*30% -> 600
B18: INVESTIMENTO MENSAL
B19: Quanto vou investir por mês? | D19: 200
B20: Por Quantos Anos? | D20: 5
B21: Taxa de Rendimento Mensal? | D21: 0.01079
B22: Patrimônio Acumulado? | D22: {=FV(taxa_mensal,qtd_anos*12,aporte*-1)} -> 16755.383
B23: Dividendos Mensais? | D23: {=patrimonio*rendimento_carteira} -> 100.5323
B25: Cenários | D25: Dividendo
B26: Quanto em 2 Anos? | C26: =FV($D$21,$A27*12,$D$19*-1) -> 5445.5255 | D26: {=C26*rendimento_carteira} -> 32.673153
A27: 2 | B27: Quanto em 5 Anos? | C27: =FV($D$21,$A28*12,$D$19*-1) -> 16755.383 | D27: {=C27*rendimento_carteira} -> 100.5323
A28: 5 | B28: Quanto em 10 Anos? | C28: =FV($D$21,$A29*12,$D$19*-1) -> 48656.843 | D28: {=C28*rendimento_carteira} -> 291.94106
A29: 10 | B29: Quanto em 20 Anos? | C29: =FV($D$21,$A30*12,$D$19*-1) -> 225039.68 | D29: {=C29*rendimento_carteira} -> 1350.2381
A30: 20 | B30: Quanto em 30 Anos? | C30: =FV($D$21,$A31*12,$D$19*-1) -> 864433.93 | D30: {=C30*rendimento_carteira} -> 5186.6036
A31: 30
B32: PERFIL | C32: Moderado
B33: VALOR A SER INVESTIDO POR MÊS | C33: {=aporte} -> 200
B35: TIPO DE FII | C35: PERCENTUAL SUGERIDO | D35: VALORES
B36: PAPEL | C36: =VLOOKUP($C$32&"-"&B36,Chave!$A:$D,4,FALSE) -> 0.32 | D36: =C36*$C$33 -> 64
B37: TIJOLO | C37: =VLOOKUP($C$32&"-"&B37,Chave!$A:$D,4,FALSE) -> 0.35 | D37: =C37*$C$33 -> 70
B38: HÍBRIDOS | C38: =VLOOKUP($C$32&"-"&B38,Chave!$A:$D,4,FALSE) -> 0.08 | D38: =C38*$C$33 -> 16
B39: FOFs | C39: =VLOOKUP($C$32&"-"&B39,Chave!$A:$D,4,FALSE) -> 0.05 | D39: =C39*$C$33 -> 10
B40: DESENVOLVIMENTO | C40: =VLOOKUP($C$32&"-"&B40,Chave!$A:$D,4,FALSE) -> 0.1 | D40: =C40*$C$33 -> 20
B41: HOTELARIAS | C41: =VLOOKUP($C$32&"-"&B41,Chave!$A:$D,4,FALSE) -> 0.1 | D41: =C41*$C$33 -> 20
D42: =SUM(D36:D41) -> 200

Sheet Chave
A2: CHAVE | B2: PERFIL | C2: TIPO DE FII | D2: %
A3: =B3&"-"&C3 -> Conservador-PAPEL | B3: Conservador | C3: PAPEL | D3: 0.3
A4: =B4&"-"&C4 -> Conservador-TIJOLO | B4: Conservador | C4: TIJOLO | D4: 0.5
A5: =B5&"-"&C5 -> Conservador-HÍBRIDOS | B5: Conservador | C5: HÍBRIDOS | D5: 0.1
A6: =B6&"-"&C6 -> Conservador-FOFs | B6: Conservador | C6: FOFs | D6: 0.1
A7: =B7&"-"&C7 -> Conservador-DESENVOLVIMENTO | B7: Conservador | C7: DESENVOLVIMENTO | D7: 0
A8: =B8&"-"&C8 -> Conservador-HOTELARIAS | B8: Conservador | C8: HOTELARIAS | D8: 0
A9: =B9&"-"&C9 -> Moderado-PAPEL | B9: Moderado | C9: PAPEL | D9: 0.32
A10: =B10&"-"&C10 -> Moderado-TIJOLO | B10: Moderado | C10: TIJOLO | D10: 0.35
A11: =B11&"-"&C11 -> Moderado-HÍBRIDOS | B11: Moderado | C11: HÍBRIDOS | D11: 0.08
A12: =B12&"-"&C12 -> Moderado-FOFs | B12: Moderado | C12: FOFs | D12: 0.05
A13: =B13&"-"&C13 -> Moderado-DESENVOLVIMENTO | B13: Moderado | C13: DESENVOLVIMENTO | D13: 0.1
A14: =B14&"-"&C14 -> Moderado-HOTELARIAS | B14: Moderado | C14: HOTELARIAS | D14: 0.1
... A20: =B20&"-"&C20 -> Agressivo-HOTELARIAS | B20: Agressivo | C20: HOTELARIAS | D20: 0.1
